src/__init__.py
src/__main__.py
src/classes.py
wiselang-1.0.5.dist-info/LICENSE
wiselang-1.0.5.dist-info/METADATA
wiselang-1.0.5.dist-info/WHEEL
wiselang-1.0.5.dist-info/top_level.txt
wiselang-1.0.5.dist-info/RECORD
