Metadata-Version: 2.1
Name: wiselang
Version: 1.0.5
Summary: A Wise language, for wise members of AUI
Author: BLA4KM4MBA, SEG-V
Author-email: tarunpreetsingh@protonmail.com
License: UNKNOWN
Project-URL: Website, https://bla4km4mba.github.io/wiselang-site
Project-URL: Wiki, https://github.com/BLA4KM4MBA/WiseLang/wiki
Project-URL: Docs, https://bla4km4mba.github.io/wiselang-site/docs.html
Keywords: python,language,esoteric,wise,hindi
Platform: UNKNOWN
Classifier: Development Status :: 1 - Planning
Classifier: Intended Audience :: Developers
Classifier: Programming Language :: Python :: 3
Classifier: Operating System :: Unix
Classifier: Operating System :: MacOS :: MacOS X
Classifier: Operating System :: Microsoft :: Windows
License-File: LICENSE
Requires-Dist: sly
